smartdance/__init__.py
smartdance/exceptions.py
smartdance/smartdance.py
smartdance/utils.py
smartdance-3.0.0.dist-info/METADATA
smartdance-3.0.0.dist-info/WHEEL
smartdance-3.0.0.dist-info/top_level.txt
smartdance-3.0.0.dist-info/RECORD
