Metadata-Version: 2.1
Name: smartdance
Version: 3.0.0
Summary: A Python package for template string processing designed for prompt engineering
Home-page: UNKNOWN
Author: Marcelo Arias
Author-email: marcelo@smartup.lat
License: UNKNOWN
Platform: UNKNOWN
Classifier: Development Status :: 3 - Alpha
Classifier: Intended Audience :: Developers
Classifier: License :: OSI Approved :: MIT License
Classifier: Programming Language :: Python :: 3.6
Classifier: Programming Language :: Python :: 3.7
Classifier: Programming Language :: Python :: 3.8
Classifier: Programming Language :: Python :: 3.9
